[
  {
    "chunk_index": 19,
    "text": "# Authorized representative requirements\n\nTo verify your business, we require information about the **Authorized Representative** who is completing this onboarding process on behalf of your legal entity.\n\n## Who is the Authorized Representative?\n\nThe **Authorized Representative is the individual who is currently filling out the Xendit onboarding application on behalf of your company**. This person will be our primary point of contact for the application process and must be legally empowered to sign documents and make commitments for the business.\n\n![](https://cdn.document360.io/217abc43-8677-41fb-a81d-fceeb1fa0358/Images/Documentation/image-1761282186132.png?sv=2022-11-02&spr=https&st=2026-04-23T06%3A20%3A55Z&se=2026-04-23T06%3A32%3A55Z&sr=c&sp=r&sig=EHNDxDwWlwOjMnM7QkIQfmTWTGfex77hxPqY75UYVno%3D)\n\n## Required information\n\nThe Authorized Representative must complete the following fields in the onboarding flow:\n\n| Category | Required Details |\n| --- | --- |\n| Personal Details | First Name, Last Name, Gender, Date of Birth |\n| Contact Information | Email Address, Phone Number |\n| Residential Address | Full Residential Address (Country, Address Line 1, City, State/Province, Postal Code) |\n| Nationality | Country of Citizenship/Nationality |\n| Role | The representative's official role within the company. |\n\n---\n\n## Required verification documents\n\nTo confirm the identity and authority of the representative, the following documents must be submitted:\n\n1. #### Proof of Identity\n\n   You must upload a clear copy of a valid government-issued ID. You will be prompted to select the type of ID you are submitting:\n\n- National ID (e.g., KTP, NRIC)\n- Passport\n\n*Please ensure the ID is valid (not expired) and that the photo, full name, and ID number are clearly visible.*\n\n**List of Acceptable ID Documents**\n\n####\n\n2. #### Proof of Address\n\n   If your government-issued ID does **NOT** contain your residential address, you will be prompted to upload a separate document displaying your address\n\n   1. Any official document that states your residential address (e.g. utility bill, phone bill, tenancy agreement, etc.)\n   2. Document must include your full name\n   3. Document must be a digital download, not scanned or photographed from a physical document\n3. #### Proof of Authorization\n\n   This document verifies that the **Authorized Representative has the legal right to act on behalf of the company** for the purpose of onboarding with Xendit.\n\n- If the representative is **declared in the legal documents submitted, and based on your country’s legal requirements, they are recognized as the authorized representative, you do not need to upload a separate document.**\n- If the representative is **NOT** **legally able to represent the company by their role/title, you MUST upload a formal document proving their authority**, such as:\n\n  - **Board Resolution Granting Authority**: A resolution signed by at least two (2) Directors and one (1) Company Secretary. This document must clearly state that you are authorized to represent and verify the company's details.\n  - **Letter of Authorization (LOA)**: A formal letter on company letterhead signed by a legally authorized person (e.g. Director) explicitly granting you the authority to complete the Xendit application.\n\n## Liveness Verification test\n\nAs a final step to verify that the Authorized Representative is a real person and that the submitted documents belong to them, you will be required to complete an active Liveness Verification test.\n\n![](https://cdn.document360.io/217abc43-8677-41fb-a81d-fceeb1fa0358/Images/Documentation/image(153).png?sv=2022-11-02&spr=https&st=2026-04-23T06%3A20%3A55Z&se=2026-04-23T06%3A32%3A55Z&sr=c&sp=r&sig=EHNDxDwWlwOjMnM7QkIQfmTWTGfex77hxPqY75UYVno%3D)\n\nThis process involves using your device's camera to capture a series of movements or actions:\n\n- **Be prepared:** Ensure you are in a well-lit area and that your face is clearly visible.\n- **Follow the prompts:** The system will guide you through simple actions (e.g., moving your head) to confirm you are present and alive.\n- **Camera Access:** Make sure Xendit has permission to access your camera and that no other applications are currently using it.\n- **Microphone Access (in some cases):** Make sure Xendit has permission to access your microphone and that no other applications are currently using it.\n\nNote: You must pass the liveness verification for the onboarding process to be complete. If you encounter issues (like \"Camera not accessible\"), you may need to check your browser or operating system settings to grant access.",
    "metadata": {
      "url": "https://docs.xendit.co/docs/authorized-representative-requirements",
      "title": "Authorized representative requirements",
      "description": "''",
      "section": "docs",
      "scraped_at": "'2026-04-23T06:21:01.882167Z'",
      "source": "https://docs.xendit.co",
      "breadcrumbs": "",
      "chunk_index": 19,
      "source_file": "authorized-representative-requirements.md"
    }
  }
]