[
  {
    "chunk_index": 57,
    "text": "# Card declines and error codes\n\nWhen a customer's credit or debit card transaction is declined, it can be frustrating for both the customer and the merchant. At Xendit, we've optimized our system to minimize declines originating from the acquiring bank. This means most declines you encounter are likely due to the issuing bank—the bank that issued the customer's card.\n\n## Why do declines happen?\n\nIssuing banks are the primary source of decline information, but they only share the exact reason directly with the cardholder. To get details, the cardholder must contact their bank, providing transaction specifics like the amount and date.\n\nSince asking every customer to call their bank isn't practical, Xendit uses heuristics. These are intelligent estimates based on signals from the issuing bank and regional factors, helping us determine the most probable reasons for declines. These insights are available in the **Decline Insights** section of the Card Transaction Details page in your Xendit Dashboard.\n\n## Xendit decline reasons and network response codes\n\nFor a comprehensive list of Xendit's specific error and failure codes, please refer to [this page](/docs/error-scenarios).\n\nIn addition to Xendit's codes, card networks also return their own error codes. These are provided as additional data in our API responses, giving you more granular information about a decline.\n\nHere's an example of a network response:\n\nCustom\n\n```\n\"payment_details\": {\n    //payment detail fields\n    \"authorization_data\": {\n        \"card_network_response_code\": \"65\",\n        \"card_network_descriptor\": \"Exceeds withdrawal count limit\",\n        \"merchant_advice_code\": \"28\",\n        \"merchant_advice_descriptor\": \"Retry after 6 days\",\n        \"three_ds_trans_status\": \"Y\",\n        \"three_ds_flow\": \"CHALLENGE\"\n    }\n}\n```\n\nJSON\n\nCopy\n\n## Network response code data\n\n- `card_network_response_code` - The response code returned by the scheme (Visa, Mastercard, JCB, China Unionpay or Amex)\n- `card_network_descriptor` - Description of the response code\n- `merchant_advice_code` - Only returned when present, only returned for Mastercard. Mastercard has codes which describe what action to take towards merchants. Not following Mastercard's advice may lead to \"excessive retry fines\". These fines can go up to USD 0.50 per transaction.\n- `merchant_advice_descriptor` - Only returned when present. Only returned for Mastercard. Description / action to take for the merchant advice code.\n- `three_ds_trans_status` - The `transStatus` result, directly from the 3DS2 response, indicating the authentication status of the transaction.\n- `three_ds_flow` - The 3DS2 authentication flow the customer experienced when completing 3DS2.\n\n## Card network response codes\n\n### `TransStatus` (`three_ds_trans_status`) and 3DS Flow (`three_ds_flow`)\n\n`three_ds_trans_status` Indicates whether a transaction was authenticated, as per EMVCo 3DS2 specification.\n\n#### Possible values:\n\n| Error / response code | Description |\n| --- | --- |\n| Y | Account verification successful |\n| I | Authentication / Exemption granted by Issuer |\n| N | Not Authenticated / account not verified, challenge failed |\n| U | Authentication / account verification could not be performed (could be due to authentication not being available for the card/issuer). Could potentially still proceed with transaction, if no 3DS is enabled |\n| A | Authentication / verification was attempted |\n| C | Challenge Required. Additional authentication is required using a challenge |\n| R | Authentication / account verification rejected by the issuer. |\n\n`three_ds_flow` can return either FRICTIONLESS or CHALLENGE, indicating which flow the shopper has gone through when completing 3DS2.\n\n#### Possible values:\n\n| Value | Description |\n| --- | --- |\n| FRICTIONLESS | The shopper went through a [frictionless 3DS flow](/v1/docs/authentication-3ds2) |\n| CHALLENGE | The shopper went through a [challenge 3DS flow](/v1/docs/authentication-3ds2) |\n\n## Mastercard Merchant Advice Codes\n\nMerchant advice codes provide guidance on handling declined transactions. These codes help you understand why a transaction was declined and what actions to take next.\n\nA Mastercard merchant advice code will usually come in combination with one of the following `card_network_response_code` codes: 14, 41, 43, 54, 57, 62, 65, 75, 82, 83, 85, 91, 93 and 96 ([explained in the overview](/docs/cards-card-declines-and-error-codes#card-network-response-code-overview-cardnetworkresponsecode)).\n\n### How to use Mastercard merchant advice codes:\n\n- **Identify the Decline Reason:** \\\n  Each code corresponds to a specific reason for decline. Use it to determine whether the issue is technical, policy-related, or cardholder-specific.\n\n  - Example: Code 03 — Don't retry, penalty fees may apply. Consider contacting the cardholder.\n- **Actionable vs. Non-actionable Codes: Some codes suggest retrying, while others require no further action.**\n\n  - Example: Code 24 — Retry after 1 hour.\n  - Code 40 — No action required.\n- **Avoid Penalties: Codes may warn of penalties for retrying certain transactions.**\n\n  - Example: Code 21 — Don't retry, penalty fees may apply.\n- **Contact Support for Technical Issues: If the code refers to technical problems, direct developers to reach out to support**.\n\n  - Example: Code 04 — Contact support for token issues.\n- **Installments and Recurring Payments: Some codes indicate restrictions on specific payment types, like installments.**\n\n  - Example: Code 22 — Installments not allowed, do not retry.\n\nBy integrating these codes into your payment processing logic, you can handle declined transactions appropriately, avoid penalties, and provide better guidance to merchants.\n\n#### Possible values:\n\n| Code | Description | Additional information |\n| --- | --- | --- |\n| 1 | Update card information | Ask the shopper to provide new card information |\n| 2 | Try the again payment after 72 hours. |  |\n| 3 | Do not retry this payment. Retries can be subject to penalty fees by Mastercard. Consider reaching out directly to the shopper. |  |\n| 4 | Technical token issue, reach out to Xendit support. |  |\n| 8 | Blocked by payment processor. | Contact Xendit support |\n| 21 | Do not retry this payment. Retries can be subject to penalty fees by Mastercard. | Penalties can go up to USD$0.50 per call. |\n| 22 | Do not retry this payment, installments not allowed for this transaction. | Installments are not supported |\n| 24 | Retry the payment after 1 hour. |  |\n| 25 | Retry the payment after 24 hours. |  |\n| 26 | Retry the payment after 2 days. |  |\n| 27 | Retry the payment after 4 days. |  |\n| 28 | Retry the payment after 6 days. |  |\n| 29 | Retry the payment after 8 days. |  |\n| 30 | Retry the payment after 10 days. |  |\n| 40 | No action required. |  |\n| 41 | No action required. |  |\n| 42 | No action required. |  |\n| 99 | No action possible. |  |\n\n## Card network response code overview (`card_network_response_code)`\n\n| **Network response code** | **Description** | **Action** | **Xendit mapped code** | **Additional information** |\n| --- | --- | --- | --- | --- |\n| 01 | Refer to card issuer | Recommend cardholder to contact their card issuing bank to resolve the problem on online transaction Or, try to use different card. Or, use other form of payment. | DECLINED\\_BY\\_ISSUER |  |\n| 02 | Refer to card issuer | Shopper to contact the card issuer | DECLINED\\_BY\\_ISSUER |  |\n| 03 | Invalid merchant | Reach out to Xendit | DECLINED\\_BY\\_ISSUER |  |\n| 04 | Capture card | Retain card | STOLEN\\_CARD |  |\n| 05 | Do not honor | Try again using a different card | DECLINED\\_BY\\_ISSUER | Often used by issuers when they don't trust a transaction or did not properly map a different error code. |\n| 06 | Try again using a different card | Try again using a different card | DECLINED\\_BY\\_ISSUER |  |\n| 07 | Pick up card, special condition (fraud account) | - | STOLEN\\_CARD | Used in physical situations, telling merchants to retain the card |\n| 10 | Partial Approval | - | PARTIAL\\_APPROVAL | A partial amount was accepted, the rest of the transaction needs to be completed using a different card. |\n| 11 | Approved (V.I.P) | - | SUCCESS | Used by visa when they stand in for the issuer, accepting a transaction on behalf of. |\n| 12 | Invalid transaction | Do not try again | INACTIVE\\_OR\\_UNAUTHORIZED\\_CARD |  |\n| 13 | Invalid amount | Use a different amount | INACTIVE\\_OR\\_UNAUTHORIZED\\_CARD |  |\n| 14 | Invalid card number | Try again with a different card (number) | INVALID\\_CARD |  |\n| 15 | Invalid issuer | Retry at a later time | INVALID\\_CARD |  |\n| 19 | Re-enter transaction | Retry the transaction | PROCESSOR\\_ERROR |  |\n| 21 | Payment cancellation | Do not retry | DECLINED\\_BY\\_ISSUER | The user cancelled the transaction during processing, only relevant on EDC |\n| 25 | Unable to locate record in file | Reach out to Xendit support | PROCESSOR\\_ERROR | This will not occur |\n| 28 | File temporarily not available for update or inquiry | Reach out to Xendit support | PROCESSOR\\_ERROR | Indicator of problems on the scheme side |\n| 30 | Format error | The card issuer does not recognize the transaction details being entered. This is due to a format error. The shopper should check the transaction information and try again. | PROCESSOR\\_ERROR |  |\n| 39 | No credit account | Try again using a different card | INVALID\\_CVV | The card is not suitable for this type of transactino. For example when adttempting to use prepaid for recurring. |\n| 41 | Stolen card | Do not retry | STOLEN\\_CARD |  |\n| 42 | Processor error | Try again in a few minutes | PROCESS\\_ERROR | Recommend cardholder to try again in a few minutes. Alternatively, they can try to use other form of payment. |\n| 43 | Stolen card | Do not retry | STOLEN\\_CARD |  |\n| 46 | Closed account | Try again using a different card | INACTIVE\\_OR\\_UNAUTHORIZED\\_CARD |  |\n| 51 | Insufficient funds |  | INSUFFICIENT\\_BALANCE |  |\n| 52 | No checking account |  | PROCESSOR\\_ERROR |  |\n| 53 | No savings account |  | PROCESSOR\\_ERROR |  |\n| 54 | Expired card |  | EXPIRED\\_CARD | Could also mean expiration date is missing |\n| 55 | Invalid PIN |  | INACTIVE\\_OR\\_UNAUTHORIZED\\_CARD |  |\n| 57 | Transaction not permitted to cardholder | Retry with a different card | INACTIVE\\_OR\\_UNAUTHORIZED\\_CARD | The card is not suitable for this type of transactino. For example when adttempting to use prepaid for recurring. |\n| 58 | Transaction not permitted |  | DECLINED\\_BY\\_ISSUER |  |\n| 59 | Suspected fraud |  | ISSUER\\_SUSPECT\\_FRAUD | Issuer suspects fraud |\n| 61 | Limit exceeded |  | INSUFFICIENT\\_BALANCE |  |\n| 62 | Restricted card | Shopper could contact issuer or use a different card | DECLINED\\_BY\\_ISSUER | Card no. valid in country or region |\n| 63 | Security violation |  | DECLINED\\_BY\\_ISSUER |  |\n| 64 | Card declined |  | DECLINED\\_BY\\_PROCESSOR |  |\n| 65 | Limit exceeded |  | DECLINED\\_BY\\_ISSUER |  |\n| 70 | Contact card issuer |  | DECLINED\\_BY\\_ISSUER |  |\n| 71 | PIN not changed |  | CARD\\_DECLINED | Does not happen on eCommerce |\n| 72 | Account not yet active | Only happens for Mastercard | DECLINED\\_BY\\_ISSUER |  |\n| 74 | Invalid PIN |  | DECLINED\\_BY\\_PROCESSOR |  |\n| 75 | Allowable number of PIN tries exceeded |  | DECLINED\\_BY\\_ISSUER |  |\n| 78 | Invalid / nonexistent account specified (general) |  | INACTIVE\\_OR\\_UNAUTHORIZED\\_CARD | The transaction is from a new cardholder and the card has not been properly unblocked or activated. |\n| 79 | Life cycle |  | DECLINED\\_BY\\_PROCESSOR | Mastercard only |\n| 80 | Credit issuer unavailable |  | PROCESSOR\\_ERROR |  |\n| 81 | Suspected fraud |  | DECLINED\\_BY\\_PROCESSOR |  |\n| 82 | Invalid CVN |  | INVALID\\_CVV | Do not tell shoppers their CVN was invalid, this may help fraudsters. |\n| 83 | Suspected fraud |  | ISSUER\\_SUSPECT\\_FRAUD |  |\n| 84 | Invalid authorization life cycle |  | DECLINED\\_BY\\_ISSUER |  |\n| 85 | Approved |  | SUCCESS |  |\n| 86 | Invalid PIN |  | DECLINED\\_BY\\_PROCESSOR |  |\n| 87 | Purchase amount only, no cash back allowed |  | CARD\\_DECLINED |  |\n| 88 | Cryptographic failure |  | CARD\\_DECLINED |  |\n| 89 | Ineligible to receive financial position information (GIV) |  | PROCESSOR\\_ERROR |  |\n| 90 | Cutoff is in progress | Retry at a later stage | CARD\\_DECLINED |  |\n| 91 | Temporary system error | Retry at a later stage | ISSUER\\_UNAVAILABLE |  |\n| 92 | Temporary system error | Retry at a later stage | INACTIVE\\_OR\\_UNAUTHORIZED\\_CARD |  |\n| 93 | Transaction cannot be completed - violation of law |  | DECLINED\\_BY\\_ISSUER |  |\n| 94 | Duplicated transaction | Do not retry | DECLINED\\_BY\\_PROCESSOR |  |\n| 96 | System error |  | ISSUER\\_UNAVAILABLE |  |\n| 1A | Authentication required | Authentication needed for this transaction. Try again using authentication | AUTHENTICATION\\_FAILED | Visa only |\n| 1Z | Temporary system error |  | PROCESSOR\\_ERROR |  |\n| 9G | Blocked by cardholder/contact cardholder | The cardholder blocked this card. Ask the cardholder to use another payment method | CARD\\_DECLINED | Visa only |\n| 5C | Transaction not supported/blocked by issuer | The transaction was refused by the card issuer. The shopper can contact their bank or try with a different payment method. | DECLINED\\_BY\\_ISSUER | Visa only |\n| B1 | Surcharge amount not permitted on Visa cards or EBT food stamps (U.S. acquirers only) |  | DECLINED\\_BY\\_PROCESSOR |  |\n| B2 | Surcharge amount not supported by debit network issuer |  | DECLINED\\_BY\\_PROCESSOR |  |\n| N0 | Force STIP |  | PROCESSOR\\_ERROR |  |\n| N3 | Issuer not available |  | DECLINED\\_BY\\_ISSUER |  |\n| N4 | Limit exceeded |  | INSUFFICIENT\\_BALANCE |  |\n| N5 | Ineligible for resubmission |  | PROCESSOR\\_ERROR |  |\n| N7 | Invalid CVN |  | INVALID\\_CVV |  |\n| N8 | Preauthorized amount exceeded |  | DECLINED\\_BY\\_PROCESSOR |  |\n| P6 | Denied PIN |  | CARD\\_DECLINED |  |\n| Q1 | Authentication failed |  | PROCESSOR\\_ERROR |  |\n| R0 | Stop payment order |  | DECLINED\\_BY\\_ISSUER |  |\n| R1 | Revocation of authorization order |  | TRANSACTION\\_BLOCKED |  |\n| R2 | Transaction does not qualify for Visa PIN |  | DECLINED\\_BY\\_ISSUER |  |\n| R3 | Revocation of authorization order |  | DECLINED\\_BY\\_ISSUER |  |\n| Z3 | Not available for online transaction |  | DECLINED\\_BY\\_ISSUER |  |\n\n\\\n\n## Handling 3DS Response Details: Three DS transaction status reason & Three DS challenge cancel code\n\nWhen a 3DS authentication completes, your integration receives a primary `three_ds_trans_status` (Transaction Status) code from the authentication webhook event. While codes like Y (Success) are simple, handling failures (N, U, or R) requires more detail.\n\nThis is where `three_ds_trans_status_reason` and `three_ds_challenge_cancel_code` become essential. They provide the specific \"why\" behind a failed or incomplete authentication, allowing you to build a robust handler, debug issues, and provide clear feedback to your users.\n\n### Three DS trans status reason (`three_ds_trans_status_reason`)\n\nThis is the primary reason code for the authentication outcome. It's sent by the issuer's bank (the ACS) and explains *why* the transaction received its final `three_ds_trans_status`.\n\nYou should always check this parameter when the `three_ds_trans_status` is:\n\n- N (Not Authenticated)\n- U (Unable to Authenticate)\n- R (Rejected by Issuer)\n\nThe detail of the `three_ds_trans_status_reason` can be seen in this table below\n\n| **Transaction Status Reason** | **Transaction Status Reason Descriptor** | **Actionable Insight for Merchant** | **Xendit Failure Reason** |\n| --- | --- | --- | --- |\n| 1 | Card authentication failed | This is a general failure. The issuer's risk assessment resulted in a negative outcome. This could be based on a combination of factors in the AReq data that the merchant sent. | AUTHENTICATION\\_FAILED |\n| 2 | Unknown Device | The device used for the transaction is not recognized by the issuer. This highlights the importance of comprehensive device data collection. Merchants with mobile apps using our 3DS SDK are better positioned to avoid this | AUTHENTICATION\\_FAILED |\n| 3 | Unsupported Device | The device does not support the 3DS authentication methods requested by the issuer. | AUTHENTICATION\\_FAILED |\n| 4 | Exceeds authentication frequency limit | The cardholder has been authenticated too many times recently. This is a velocity check by the issuer to prevent potential fraudulent activity. | AUTHENTICATION\\_FAILED |\n| 5 | Expired card | The card used in the transaction has expired. This is a basic data validation that should ideally be caught by the merchant's systems even before initiating 3DS. | AUTHENTICATION\\_FAILED |\n| 6 | Invalid card number | The card number failed a basic Luhn check or is otherwise invalid. Again, this points to a need for front-end validation | AUTHENTICATION\\_FAILED |\n| 7 | Invalid transaction | The issuer deemed the transaction type or context invalid. This could be due to scheme rules or issuer-specific policies. | AUTHENTICATION\\_FAILED |\n| 8 | No Card record | The issuer has no record of this account number. This could indicate a mistyped card number or a card from an issuer not participating in 3DS. | AUTHENTICATION\\_FAILED |\n| 9 | Security failure | A security issue was detected during the authentication process. This is a serious flag indicating a potential threat. | AUTHENTICATION\\_FAILED |\n| 10 | Stolen card | The card has been reported as stolen. | AUTHENTICATION\\_FAILED |\n| 11 | Suspected fraud | The issuer's risk scoring engine has flagged the transaction as highly suspicious based on the data provided. This is a strong signal for the merchant to decline the transaction. | AUTHENTICATION\\_FAILED |\n| 12 | Transaction not permitted to cardholder | The issuer has placed a restriction on the account that prevents this type of transaction (e.g., international purchases blocked). | AUTHENTICATION\\_FAILED |\n| 13 | Cardholder not enrolled in service | The cardholder has not yet registered for the issuer's authentication service (e.g., has not set up their banking app for approvals). | AUTHENTICATION\\_FAILED |\n| 14 | Transaction timed out at the ACS | The issuer's system was too slow to respond. Please retry the request after one minute. | AUTHENTICATION\\_FAILED |\n| 15 | Low Confidence | This code indicates the issuer's confidence level in their authentication assessment, even if it results in a failure. | AUTHENTICATION\\_FAILED |\n| 16 | Medium Confidence | This code indicates the issuer's confidence level in their authentication assessment, even if it results in a failure. | AUTHENTICATION\\_FAILED |\n| 17 | High Confidence | This code indicates the issuer's confidence level in their authentication assessment, even if it results in a failure | AUTHENTICATION\\_FAILED |\n| 18 | Very High Confidence | This code indicates the issuer's confidence level in their authentication assessment, even if it results in a failure. | AUTHENTICATION\\_FAILED |\n| 20 | Non-payment transaction not supported | You attempted a non-payment 3DS check, but the issuer does not support it for this card. Do not re-attempt non-payment 3DS for this card | AUTHENTICATION\\_FAILED |\n| 21 | 3RI transaction not supported | You attempted a merchant-initiated (3RI) 3DS check, but the issuer does not support it for this card. Do not re-attempt 3RI 3DS for this card; make a risk decision to authorize without it | AUTHENTICATION\\_FAILED |\n| 22 | ACS technical issue | The issuer's system experienced a technical problem that prevented authentication. Please retry with another request. | AUTHENTICATION\\_FAILED |\n| 23 | Decoupled authentication required by ACS but not requested by 3DS requestor | The issuer wanted to use an out-of-band/decoupled authentication (like a banking app push notification) but the merchant did not signal support for it. | AUTHENTICATION\\_FAILED |\n| 24 | 3DS requestor decoupled max expiry time exceeded | The decoupled challenge was in progress, but got timed out. | AUTHENTICATION\\_FAILED |\n| 25 | Low-latency Decoupled Authentication was provided insufficient time to authenticate the Cardholder. The ACS will not make an attempt to authenticate the Cardholder. | The ACS refused to even start the decoupled challenge | AUTHENTICATION\\_FAILED |\n| 26 | Authentication attempted but not performed by the cardholder | An attempt was made, but for some reason (often cardholder inaction), it wasn't completed. Please retry with another request | AUTHENTICATION\\_FAILED |\n| 27-79 | Reserved for EMVCo future use |  | AUTHENTICATION\\_FAILED |\n| 80-99 | Reserved for DS use |  | AUTHENTICATION\\_FAILED |\n\n### Challenge Cancel Code (`three_ds_challenge_cancel_code`)\n\nThis parameter is more specific. It only applies if a challenge was presented and then cancelled. It tells you *why* the challenge window was dismissed.\n\nYou should check this parameter if `three_ds_trans_status` is N and `three_ds_trans_status_reason` is 26 (Authentication Not Performed). This combination gives you the full story.\n\n\\\n\n#### Implementing Your Response Handler (Putting It Together)\n\nUse this logic as a starting point for your server-side handler.\n\n#### Example Scenario\n\nA shopper is presented with a 3DS challenge. They get confused and click the \"Cancel\" button.\n\nHere is the data your server will likely receive:\n\n- three\\_ds\\_trans\\_status: N (Not Authenticated)\n- three\\_ds\\_trans\\_status\\_reason: 26 (Authentication Not Performed)\n- three\\_ds\\_challenge\\_cancel\\_code: 01 (Cardholder Selected \"Cancel\")\n\nThis structure allows you to properly handle failures, provide clear feedback, and maintain excellent logs for debugging.\n\n#### The detail of the three\\_ds\\_challenge\\_cancel\\_code can be seen in this table below\n\n| **Challenge Cancel Code** | **Challenge Cancel Code Descriptor** | **Xendit Failure Reason** |\n| --- | --- | --- |\n| 1 | Cardholder selected Cancel. | AUTHENTICATION\\_FAILED |\n| 2 | Reserved for future EMVCo use (values invalid until defined by EMVCo). | AUTHENTICATION\\_FAILED |\n| 3 | Transaction timed out—Decoupled Authentication. | TIMEOUT\\_ERROR |\n| 4 | Transaction timed out at ACS—other timeouts. | TIMEOUT\\_ERROR |\n| 5 | Transaction timed out at ACS—First CReq not received by ACS. | TIMEOUT\\_ERROR |\n| 6 | Transaction Error. | PROCESSOR\\_ERROR |\n| 7 | Unknown. | PROCESSOR\\_ERROR |\n| 8 | Transaction timed out at SDK. | TIMEOUT\\_ERROR |",
    "metadata": {
      "url": "https://docs.xendit.co/docs/cards-card-declines-and-error-codes",
      "title": "Card declines and error codes",
      "description": "Learn why credit card declines happen and how Xendit helps merchants",
      "section": "docs",
      "scraped_at": "'2026-04-23T06:19:38.537343Z'",
      "source": "https://docs.xendit.co",
      "breadcrumbs": "",
      "chunk_index": 57,
      "source_file": "cards-card-declines-and-error-codes.md"
    }
  }
]